slack_alerts/__init__.py
slack_alerts/alerter.py
slack_alerts/elements.py
slack_alerts/exceptions.py
slack_alerts/utils.py
slack_alerts-1.0.0.dist-info/WHEEL
slack_alerts-1.0.0.dist-info/METADATA
slack_alerts-1.0.0.dist-info/RECORD
